[{
  "_id": {
    "$oid": "65e5540a0dbd43bdac264d3f"
  },
  "comment": "No se que poner",
  "creator": {
    "$oid": "65e54bee7127a315e21367d2"
  },
  "condition": true,
  "__v": 0
},
{
  "_id": {
    "$oid": "65e556a24fd9a1d6b843f82c"
  },
  "comment": "Ya supe que poner 2",
  "creator": {
    "$oid": "65e54bee7127a315e21367d2"
  },
  "condition": false,
  "__v": 0
},
{
  "_id": {
    "$oid": "65e557a80de4d8b0dd13cfd0"
  },
  "comment": "Comentandooo",
  "creator": {
    "$oid": "65e54bee7127a315e21367d2"
  },
  "condition": true,
  "__v": 0
},
{
  "_id": {
    "$oid": "65e557b10de4d8b0dd13cfd6"
  },
  "comment": "Comentandooo 123",
  "creator": {
    "$oid": "65e54bee7127a315e21367d2"
  },
  "condition": true,
  "__v": 0
},
{
  "_id": {
    "$oid": "65e557b70de4d8b0dd13cfdc"
  },
  "comment": "editandooo",
  "creator": {
    "$oid": "65e54bee7127a315e21367d2"
  },
  "condition": true,
  "__v": 0
}]